{
  "matchDetails": [
    {
      "homeTeam": "Louisville City FC",
      "formation": "4-1-4-1",
      "score": "2",
      "lineup": {
        "managerName": "Cruz 45‎+‎5‎'‎",
        "players": [
          {
            "shirtNumber": "28",
            "playerName": "Semmle",
            "playerPosition": "Goalkeeper",
            "playerEvents": []
          },
          {
            "shirtNumber": "15",
            "playerName": "Manny Perez",
            "playerPosition": "Defender",
            "playerEvents": [
              {
                "event": "Substitution off",
                "eventTime": "75"
              }
            ]
          },
          {
            "shirtNumber": "19",
            "playerName": "Jimenez",
            "playerPosition": "Defender",
            "playerEvents": [
              {
                "event": "Goal",
                "eventTime": "908"
              }
            ]
          },
          {
            "shirtNumber": "4",
            "playerName": "Totsch",
            "playerPosition": "Defender",
            "playerEvents": []
          },
          {
            "shirtNumber": "6",
            "playerName": "Charpie",
            "playerPosition": "Defender",
            "playerEvents": []
          },
          {
            "shirtNumber": "8",
            "playerName": "Moguel",
            "playerPosition": "Midfielder",
            "playerEvents": [
              {
                "event": "Substitution off",
                "eventTime": "85"
              }
            ]
          },
          {
            "shirtNumber": "23",
            "playerName": "Wynder",
            "playerPosition": "Midfielder",
            "playerEvents": []
          },
          {
            "shirtNumber": "36",
            "playerName": "DelPiccolo",
            "playerPosition": "Midfielder",
            "playerEvents": [
              {
                "event": "Substitution off",
                "eventTime": "61"
              }
            ]
          },
          {
            "shirtNumber": "7",
            "playerName": "Serrano",
            "playerPosition": "Midfielder",
            "playerEvents": [
              {
                "event": "Substitution off",
                "eventTime": "60"
              }
            ]
          },
          {
            "shirtNumber": "9",
            "playerName": "Gonzalez Asensi",
            "playerPosition": "Midfielder",
            "playerEvents": [
              {
                "event": "Substitution off",
                "eventTime": "60"
              }
            ]
          },
          {
            "shirtNumber": "14",
            "playerName": "Harris",
            "playerPosition": "Forward",
            "playerEvents": []
          },
          {
            "shirtNumber": "18",
            "playerName": "Faundez",
            "playerPosition": "Substitute",
            "playerEvents": []
          },
          {
            "shirtNumber": "32",
            "playerName": "Adams",
            "playerPosition": "Substitute",
            "playerEvents": [
              {
                "event": "Substitution on",
                "eventTime": "75"
              }
            ]
          },
          {
            "shirtNumber": "12",
            "playerName": "Gibson",
            "playerPosition": "Substitute",
            "playerEvents": [
              {
                "event": "Substitution on",
                "eventTime": "85"
              }
            ]
          },
          {
            "shirtNumber": "5",
            "playerName": "Pedersen",
            "playerPosition": "Substitute",
            "playerEvents": [
              {
                "event": "Substitution on",
                "eventTime": "61"
              }
            ]
          },
          {
            "shirtNumber": "17",
            "playerName": "Lancaster",
            "playerPosition": "Substitute",
            "playerEvents": []
          },
          {
            "shirtNumber": "10",
            "playerName": "Ownby",
            "playerPosition": "Substitute",
            "playerEvents": [
              {
                "event": "Substitution on",
                "eventTime": "60"
              },
              {
                "event": "Goal",
                "eventTime": "71"
              }
            ]
          },
          {
            "shirtNumber": "90",
            "playerName": "Pouwels",
            "playerPosition": "Substitute",
            "playerEvents": [
              {
                "event": "Substitution on",
                "eventTime": "60"
              }
            ]
          }
        ]
      }
    },
    {
      "awayTeam": "Oakland Roots",
      "formation": "3-4-3",
      "score": "1",
      "lineup": {
        "managerName": "Delgado",
        "players": [
          {
            "shirtNumber": "20",
            "playerName": "Blanchette",
            "playerPosition": "Goalkeeper",
            "playerEvents": [
              {
                "event": "Yellow card",
                "eventTime": "87"
              }
            ]
          },
          {
            "shirtNumber": "14",
            "playerName": "Barbir",
            "playerPosition": "Defender",
            "playerEvents": []
          },
          {
            "shirtNumber": "13",
            "playerName": "Hackshaw",
            "playerPosition": "Defender",
            "playerEvents": [
              {
                "event": "Yellow card",
                "eventTime": "81"
              }
            ]
          },
          {
            "shirtNumber": "21",
            "playerName": "Klimenta",
            "playerPosition": "Defender",
            "playerEvents": []
          },
          {
            "shirtNumber": "23",
            "playerName": "Diaz",
            "playerPosition": "Midfielder",
            "playerEvents": []
          },
          {
            "shirtNumber": "19",
            "playerName": "Prentice",
            "playerPosition": "Midfielder",
            "playerEvents": [
              {
                "event": "Substitution off",
                "eventTime": "69"
              }
            ]
          },
          {
            "shirtNumber": "7",
            "playerName": "Matsoso",
            "playerPosition": "Midfielder",
            "playerEvents": [
              {
                "event": "Substitution off",
                "eventTime": "69"
              }
            ]
          },
          {
            "shirtNumber": "6",
            "playerName": "Morad",
            "playerPosition": "Midfielder",
            "playerEvents": [
              {
                "event": "Yellow card",
                "eventTime": "53"
              }
            ]
          },
          {
            "shirtNumber": "17",
            "playerName": "Rodriguez",
            "playerPosition": "Forward",
            "playerEvents": [
              {
                "event": "Goal",
                "eventTime": "456"
              },
              {
                "event": "Substitution off",
                "eventTime": "81"
              }
            ]
          },
          {
            "shirtNumber": "10",
            "playerName": "Mfeka",
            "playerPosition": "Forward",
            "playerEvents": [
              {
                "event": "Substitution off",
                "eventTime": "70"
              }
            ]
          },
          {
            "shirtNumber": "11",
            "playerName": "Reid",
            "playerPosition": "Forward",
            "playerEvents": [
              {
                "event": "Substitution off",
                "eventTime": "85"
              }
            ]
          },
          {
            "shirtNumber": "47",
            "playerName": "Bailey",
            "playerPosition": "Substitute",
            "playerEvents": []
          },
          {
            "shirtNumber": "8",
            "playerName": "Donasiyano",
            "playerPosition": "Substitute",
            "playerEvents": [
              {
                "event": "Substitution on",
                "eventTime": "69"
              }
            ]
          },
          {
            "shirtNumber": "15",
            "playerName": "Gómez",
            "playerPosition": "Substitute",
            "playerEvents": [
              {
                "event": "Substitution on",
                "eventTime": "69"
              }
            ]
          },
          {
            "shirtNumber": "16",
            "playerName": "Her",
            "playerPosition": "Substitute",
            "playerEvents": [
              {
                "event": "Substitution on",
                "eventTime": "85"
              }
            ]
          },
          {
            "shirtNumber": "22",
            "playerName": "Cedeno",
            "playerPosition": "Substitute",
            "playerEvents": [
              {
                "event": "Substitution on",
                "eventTime": "70"
              }
            ]
          },
          {
            "shirtNumber": "18",
            "playerName": "Peláez",
            "playerPosition": "Substitute",
            "playerEvents": [
              {
                "event": "Substitution on",
                "eventTime": "81"
              }
            ]
          }
        ]
      }
    }
  ],
  "stats": {
    "GENERAL_STATS": {
      "home": {
        "Possession": "52.7%",
        "Duels_Success_Rate": "49.5%",
        "Ariel_Duels_Won": "45.5%",
        "Interceptions": "8",
        "Offsides": "0",
        "Corners_Won": "7"
      },
      "away": {
        "Possession": "47.3%",
        "Duels_Success_Rate": "50.5%",
        "Ariel_Duels_Won": "54.5%",
        "Interceptions": "7",
        "Offsides": "3",
        "Corners_Won": "3"
      }
    },
    "DISTRIBUTION_STATS": {
      "home": {
        "Passes": "417",
        "Long_Passes": "59",
        "Passing_Accuracy": "79.1%",
        "Passing_Accuracy_In_Opponent_Half": "66.9%",
        "Crosses": "29",
        "Crossing_Accuracy": "13.8%"
      },
      "away": {
        "Passes": "389",
        "Long_Passes": "66",
        "Passing_Accuracy": "75.8%",
        "Passing_Accuracy_In_Opponent_Half": "64.0%",
        "Crosses": "9",
        "Crossing_Accuracy": "33.3%"
      }
    },
    "ATTACK_STATS": {
      "home": {
        "Goals": "2",
        "Shots": "25",
        "Shots_On_Target": "10",
        "Blocked_Shots": "7",
        "Shots_Outside_Box": "10",
        "Shots_Inside_Box": "15",
        "Shooting_Accuracy": "40.0%"
      },
      "away": {
        "Goals": "1",
        "Shots": "9",
        "Shots_On_Target": "4",
        "Blocked_Shots": "4",
        "Shots_Outside_Box": "3",
        "Shots_Inside_Box": "6",
        "Shooting_Accuracy": "44.4%"
      }
    },
    "DEFENSE_STATS": {
      "home": {
        "Tackles": "12",
        "Tackle_Success_Rate": "75.0%",
        "Clearances": "9"
      },
      "away": {
        "Tackles": "9",
        "Tackle_Success_Rate": "11.1%",
        "Clearances": "33"
      }
    },
    "DISCIPLINE_STATS": {
      "home": {
        "Fouls_Conceded": "15",
        "Yellow_Cards": "0",
        "Red_Cards": "0"
      },
      "away": {
        "Fouls_Conceded": "12",
        "Yellow_Cards": "3",
        "Red_Cards": "0"
      }
    }
  },
  "events": [
    {
      "time": "3'",
      "event": "Daniel Barbir (Oakland Roots) wins a free kick in the defensive half."
    },
    {
      "time": "3'",
      "event": "Foul by Wilson Harris (Louisville City)."
    },
    {
      "time": "4'",
      "event": "Foul by Johnny Rodriguez (Oakland Roots)."
    },
    {
      "time": "4'",
      "event": "Wes Charpie (Louisville City) wins a free kick in the defensive half."
    },
    {
      "time": "5'",
      "event": "Attempt saved. Elijah Wynder (Louisville City) left footed shot from the centre of the box is saved in the centre of the goal. Assisted by Jorge González with a through ball."
    },
    {
      "time": "7'",
      "event": "Delay in match  because of an injury Neveal Hackshaw (Oakland Roots)."
    },
    {
      "time": "7'",
      "event": "Delay over. They are ready to continue."
    },
    {
      "time": "8'",
      "event": "Attempt blocked. Daniel Barbir (Oakland Roots) left footed shot from outside the box is blocked."
    },
    {
      "time": "11'",
      "event": "Attempt missed. Wolfgang Prentice (Oakland Roots) left footed shot from the left side of the box is just a bit too high. Assisted by Lindo Mfeka."
    },
    {
      "time": "12'",
      "event": "Attempt saved. Jorge González (Louisville City) right footed shot from the right side of the box is saved in the bottom right corner. Assisted by Paolo DelPiccolo."
    },
    {
      "time": "14'",
      "event": "Foul by Napo Matsoso (Oakland Roots)."
    },
    {
      "time": "14'",
      "event": "Paolo DelPiccolo (Louisville City) wins a free kick in the attacking half."
    },
    {
      "time": "16'",
      "event": "Attempt saved. Ray Serrano (Louisville City) right footed shot from the right side of the box is saved in the centre of the goal. Assisted by Paolo DelPiccolo with a through ball."
    },
    {
      "time": "16'",
      "event": "Attempt saved. Manny Perez (Louisville City) right footed shot from the right side of the box is saved in the bottom left corner."
    },
    {
      "time": "16'",
      "event": "Napo Matsoso (Oakland Roots) wins a free kick in the defensive half."
    },
    {
      "time": "16'",
      "event": "Foul by Paolo DelPiccolo (Louisville City)."
    },
    {
      "time": "16'",
      "event": "Delay in match  because of an injury Paul Blanchette (Oakland Roots)."
    },
    {
      "time": "17'",
      "event": "Delay over. They are ready to continue."
    },
    {
      "time": "19'",
      "event": "Lindo Mfeka (Oakland Roots) wins a free kick on the right wing."
    },
    {
      "time": "19'",
      "event": "Foul by Carlos Moguel Jr (Louisville City)."
    },
    {
      "time": "21'",
      "event": "Foul by Napo Matsoso (Oakland Roots)."
    },
    {
      "time": "21'",
      "event": "Oscar Jiménez (Louisville City) wins a free kick on the left wing."
    },
    {
      "time": "23'",
      "event": "Corner,  Louisville City. Conceded by Emrah Klimenta."
    },
    {
      "time": "24'",
      "event": "Corner,  Louisville City. Conceded by Neveal Hackshaw."
    },
    {
      "time": "25'",
      "event": "Attempt missed. Oscar Jiménez (Louisville City) right footed shot from more than 35 yards is high and wide to the right."
    },
    {
      "time": "26'",
      "event": "Johnny Rodriguez (Oakland Roots) wins a free kick in the defensive half."
    },
    {
      "time": "26'",
      "event": "Foul by Sean Totsch (Louisville City)."
    },
    {
      "time": "28'",
      "event": "Attempt saved. Trayvone Reid (Oakland Roots) right footed shot from outside the box is saved in the centre of the goal. Assisted by Tarek Morad."
    },
    {
      "time": "30'",
      "event": "Trayvone Reid (Oakland Roots) wins a free kick in the defensive half."
    },
    {
      "time": "30'",
      "event": "Foul by Manny Perez (Louisville City)."
    },
    {
      "time": "34'",
      "event": "Corner,  Louisville City. Conceded by Emrah Klimenta."
    },
    {
      "time": "36'",
      "event": "Attempt blocked. Jorge González (Louisville City) right footed shot from outside the box is blocked."
    },
    {
      "time": "36'",
      "event": "Trayvone Reid (Oakland Roots) wins a free kick in the defensive half."
    },
    {
      "time": "36'",
      "event": "Foul by Sean Totsch (Louisville City)."
    },
    {
      "time": "37'",
      "event": "Attempt saved. Wilson Harris (Louisville City) left footed shot from outside the box is saved in the bottom right corner. Assisted by Jorge González."
    },
    {
      "time": "38'",
      "event": "Wes Charpie (Louisville City) wins a free kick in the defensive half."
    },
    {
      "time": "38'",
      "event": "Foul by Johnny Rodriguez (Oakland Roots)."
    },
    {
      "time": "38'",
      "event": "Wolfgang Prentice (Oakland Roots) wins a free kick in the defensive half."
    },
    {
      "time": "38'",
      "event": "Foul by Ray Serrano (Louisville City)."
    },
    {
      "time": "39'",
      "event": "Napo Matsoso (Oakland Roots) wins a free kick in the defensive half."
    },
    {
      "time": "39'",
      "event": "Foul by Paolo DelPiccolo (Louisville City)."
    },
    {
      "time": "42'",
      "event": "Attempt missed. Jorge González (Louisville City) header from the centre of the box is high and wide to the left. Assisted by Oscar Jiménez with a cross."
    },
    {
      "time": "43'",
      "event": "Foul by Lindo Mfeka (Oakland Roots)."
    },
    {
      "time": "43'",
      "event": "Carlos Moguel Jr (Louisville City) wins a free kick in the defensive half."
    },
    {
      "time": "44'",
      "event": "Foul by Trayvone Reid (Oakland Roots)."
    },
    {
      "time": "44'",
      "event": "Manny Perez (Louisville City) wins a free kick on the right wing."
    },
    {
      "time": "45'",
      "event": "Foul by Trayvone Reid (Oakland Roots)."
    },
    {
      "time": "45'",
      "event": "Sean Totsch (Louisville City) wins a free kick in the defensive half."
    },
    {
      "time": "45'",
      "event": "Attempt missed. Paolo DelPiccolo (Louisville City) left footed shot from outside the box misses to the right."
    },
    {
      "time": "45+2'",
      "event": "Attempt blocked. Ray Serrano (Louisville City) right footed shot from the right side of the box is blocked."
    },
    {
      "time": "45+2'",
      "event": "Attempt blocked. Wilson Harris (Louisville City) right footed shot from outside the box is blocked."
    },
    {
      "time": "45+2'",
      "event": "Paul Blanchette (Oakland Roots) wins a free kick in the defensive half."
    },
    {
      "time": "45+2'",
      "event": "Foul by Jorge González (Louisville City)."
    },
    {
      "time": "45+4'",
      "event": "Delay in match  because of an injury Paul Blanchette (Oakland Roots)."
    },
    {
      "time": "45+4'",
      "event": "Delay over. They are ready to continue."
    },
    {
      "time": "45+6'",
      "event": "Goal!  Louisville City 0, Oakland Roots 1. Johnny Rodriguez (Oakland Roots) header from the centre of the box to the bottom right corner. Assisted by Guillermo Diaz with a cross."
    },
    {
      "time": "45+8'",
      "event": "First Half ends, Louisville City 0, Oakland Roots 1."
    },
    {
      "time": "46'",
      "event": "Foul by Trayvone Reid (Oakland Roots)."
    },
    {
      "time": "46'",
      "event": "Paolo DelPiccolo (Louisville City) wins a free kick in the defensive half."
    },
    {
      "time": "48'",
      "event": "Attempt saved. Johnny Rodriguez (Oakland Roots) left footed shot from a difficult angle on the left is saved in the bottom left corner. Assisted by Guillermo Diaz."
    },
    {
      "time": "49'",
      "event": "Corner,  Louisville City. Conceded by Trayvone Reid."
    },
    {
      "time": "50'",
      "event": "Attempt missed. Ray Serrano (Louisville City) right footed shot from outside the box is high and wide to the right following a corner."
    },
    {
      "time": "52'",
      "event": "Trayvone Reid (Oakland Roots) wins a free kick in the attacking half."
    },
    {
      "time": "52'",
      "event": "Foul by Manny Perez (Louisville City)."
    },
    {
      "time": "52'",
      "event": "Trayvone Reid (Oakland Roots) wins a free kick on the left wing."
    },
    {
      "time": "52'",
      "event": "Foul by Manny Perez (Louisville City)."
    },
    {
      "time": "53'",
      "event": "Foul by Tarek Morad (Oakland Roots)."
    },
    {
      "time": "53'",
      "event": "Elijah Wynder (Louisville City) wins a free kick on the right wing."
    },
    {
      "time": "53'",
      "event": "Tarek Morad (Oakland Roots) is shown the yellow card for a bad foul."
    },
    {
      "time": "55'",
      "event": "Lindo Mfeka (Oakland Roots) wins a free kick in the defensive half."
    },
    {
      "time": "55'",
      "event": "Foul by Elijah Wynder (Louisville City)."
    },
    {
      "time": "56'",
      "event": "Attempt missed. Jorge González (Louisville City) right footed shot from the left side of the box misses to the right. Assisted by Ray Serrano."
    },
    {
      "time": "60'",
      "event": "Substitution, Louisville City. Maarten Pouwels replaces Jorge González."
    },
    {
      "time": "60'",
      "event": "Substitution, Louisville City. Brian Ownby replaces Ray Serrano."
    },
    {
      "time": "61'",
      "event": "Substitution, Louisville City. Rasmus Thellufsen replaces Paolo DelPiccolo because of an injury."
    },
    {
      "time": "63'",
      "event": "Attempt saved. Brian Ownby (Louisville City) left footed shot from the centre of the box is saved in the bottom left corner. Assisted by Maarten Pouwels with a cross."
    },
    {
      "time": "64'",
      "event": "Attempt missed. Maarten Pouwels (Louisville City) right footed shot from the centre of the box is too high. Assisted by Brian Ownby."
    },
    {
      "time": "65'",
      "event": "Delay in match  because of an injury Wolfgang Prentice (Oakland Roots)."
    },
    {
      "time": "66'",
      "event": "Delay over. They are ready to continue."
    },
    {
      "time": "67'",
      "event": "Attempt blocked. Elijah Wynder (Louisville City) right footed shot from the centre of the box is blocked. Assisted by Brian Ownby."
    },
    {
      "time": "68'",
      "event": "Attempt saved. Carlos Moguel Jr (Louisville City) right footed shot from outside the box is saved in the bottom left corner. Assisted by Oscar Jiménez."
    },
    {
      "time": "69'",
      "event": "Substitution, Oakland Roots. Daniel Gomez replaces Wolfgang Prentice."
    },
    {
      "time": "69'",
      "event": "Substitution, Oakland Roots. Irakoze Donasiyano replaces Napo Matsoso."
    },
    {
      "time": "70'",
      "event": "Substitution, Oakland Roots. Jeciel Cedeño replaces Lindo Mfeka."
    },
    {
      "time": "71'",
      "event": "Goal!  Louisville City 1, Oakland Roots 1. Brian Ownby (Louisville City) header from the centre of the box to the bottom left corner. Assisted by Wilson Harris."
    },
    {
      "time": "72'",
      "event": "Foul by Irakoze Donasiyano (Oakland Roots)."
    },
    {
      "time": "72'",
      "event": "Elijah Wynder (Louisville City) wins a free kick in the attacking half."
    },
    {
      "time": "73'",
      "event": "Attempt saved. Carlos Moguel Jr (Louisville City) right footed shot from outside the box is saved in the top left corner."
    },
    {
      "time": "75'",
      "event": "Substitution, Louisville City. Kyle Adams replaces Manny Perez because of an injury."
    },
    {
      "time": "76'",
      "event": "Attempt blocked. Trayvone Reid (Oakland Roots) left footed shot from the left side of the box is blocked. Assisted by Daniel Barbir."
    },
    {
      "time": "76'",
      "event": "Corner,  Oakland Roots. Conceded by Kyle Adams."
    },
    {
      "time": "77'",
      "event": "Attempt blocked. Emrah Klimenta (Oakland Roots) header from the left side of the six yard box is blocked. Assisted by Guillermo Diaz with a cross."
    },
    {
      "time": "77'",
      "event": "Corner,  Oakland Roots. Conceded by Wes Charpie."
    },
    {
      "time": "78'",
      "event": "Attempt blocked. Daniel Barbir (Oakland Roots) left footed shot from the right side of the box is blocked. Assisted by Trayvone Reid."
    },
    {
      "time": "78'",
      "event": "Attempt blocked. Rasmus Thellufsen (Louisville City) right footed shot from the left side of the box is blocked. Assisted by Wilson Harris."
    },
    {
      "time": "80'",
      "event": "Corner,  Louisville City. Conceded by Guillermo Diaz."
    },
    {
      "time": "81'",
      "event": "Substitution, Oakland Roots. Anuar Peláez replaces Johnny Rodriguez."
    },
    {
      "time": "81'",
      "event": "Attempt missed. Wes Charpie (Louisville City) left footed shot from outside the box is high and wide to the left."
    },
    {
      "time": "81'",
      "event": "Neveal Hackshaw (Oakland Roots) is shown the yellow card."
    },
    {
      "time": "82'",
      "event": "Trayvone Reid (Oakland Roots) wins a free kick in the defensive half."
    },
    {
      "time": "82'",
      "event": "Foul by Wes Charpie (Louisville City)."
    },
    {
      "time": "83'",
      "event": "Offside, Oakland Roots. Daniel Gomez tries a through ball, but Anuar Peláez is caught offside."
    },
    {
      "time": "85'",
      "event": "Substitution, Louisville City. Tyler Gibson replaces Carlos Moguel Jr."
    },
    {
      "time": "85'",
      "event": "Substitution, Oakland Roots. Ryan Her replaces Trayvone Reid."
    },
    {
      "time": "87'",
      "event": "Paul Blanchette (Oakland Roots) is shown the yellow card."
    },
    {
      "time": "87'",
      "event": "Daniel Gomez (Oakland Roots) wins a free kick on the right wing."
    },
    {
      "time": "87'",
      "event": "Foul by Maarten Pouwels (Louisville City)."
    },
    {
      "time": "90'",
      "event": "Corner,  Louisville City. Conceded by Tarek Morad."
    },
    {
      "time": "90+1'",
      "event": "Attempt blocked. Maarten Pouwels (Louisville City) header from very close range is blocked. Assisted by Oscar Jiménez with a cross."
    },
    {
      "time": "90+1'",
      "event": "Foul by Daniel Gomez (Oakland Roots)."
    },
    {
      "time": "90+1'",
      "event": "Brian Ownby (Louisville City) wins a free kick on the left wing."
    },
    {
      "time": "90+2'",
      "event": "Maarten Pouwels (Louisville City) hits the right post with a header from the centre of the box. Assisted by Oscar Jiménez with a cross following a set piece situation."
    },
    {
      "time": "90+2'",
      "event": "Paul Blanchette (Oakland Roots) wins a free kick in the defensive half."
    },
    {
      "time": "90+2'",
      "event": "Foul by Wes Charpie (Louisville City)."
    },
    {
      "time": "90+3'",
      "event": "Offside, Oakland Roots. Paul Blanchette tries a through ball, but Ryan Her is caught offside."
    },
    {
      "time": "90+4'",
      "event": "Attempt saved. Anuar Peláez (Oakland Roots) right footed shot from outside the box is saved in the top right corner. Assisted by Paul Blanchette."
    },
    {
      "time": "90+4'",
      "event": "Corner,  Oakland Roots. Conceded by Oliver Semmle."
    },
    {
      "time": "90+6'",
      "event": "Offside, Oakland Roots. Neveal Hackshaw tries a through ball, but Guillermo Diaz is caught offside."
    },
    {
      "time": "90+7'",
      "event": "Foul by Ryan Her (Oakland Roots)."
    },
    {
      "time": "90+7'",
      "event": "Brian Ownby (Louisville City) wins a free kick in the attacking half."
    },
    {
      "time": "90+8'",
      "event": "Attempt blocked. Oscar Jiménez (Louisville City) right footed shot from outside the box is blocked."
    },
    {
      "time": "90+8'",
      "event": "Corner,  Louisville City. Conceded by Neveal Hackshaw."
    },
    {
      "time": "90+8'",
      "event": "Goal!  Louisville City 2, Oakland Roots 1. Oscar Jiménez (Louisville City) left footed shot from the left side of the box to the bottom right corner. Assisted by Tyler Gibson   following a corner."
    },
    {
      "time": "90+10'",
      "event": "Second Half ends, Louisville City 2, Oakland Roots 1."
    }
  ]
}