{
  "matchDetails": [
    {
      "homeTeam": "Oakland Roots",
      "formation": "3-4-3",
      "score": "0",
      "lineup": {
        "managerName": "Delgado",
        "players": [
          {
            "shirtNumber": "20",
            "playerName": "Blanchette",
            "playerPosition": "Goalkeeper",
            "playerEvents": []
          },
          {
            "shirtNumber": "14",
            "playerName": "Barbir",
            "playerPosition": "Defender",
            "playerEvents": []
          },
          {
            "shirtNumber": "13",
            "playerName": "Hackshaw",
            "playerPosition": "Defender",
            "playerEvents": []
          },
          {
            "shirtNumber": "21",
            "playerName": "Klimenta",
            "playerPosition": "Defender",
            "playerEvents": []
          },
          {
            "shirtNumber": "30",
            "playerName": "Tamacas",
            "playerPosition": "Midfielder",
            "playerEvents": [
              {
                "event": "Substitution off",
                "eventTime": "84"
              }
            ]
          },
          {
            "shirtNumber": "23",
            "playerName": "Diaz",
            "playerPosition": "Midfielder",
            "playerEvents": []
          },
          {
            "shirtNumber": "6",
            "playerName": "Morad",
            "playerPosition": "Midfielder",
            "playerEvents": [
              {
                "event": "Substitution off",
                "eventTime": "88"
              }
            ]
          },
          {
            "shirtNumber": "7",
            "playerName": "Matsoso",
            "playerPosition": "Midfielder",
            "playerEvents": [
              {
                "event": "Yellow card",
                "eventTime": "33"
              }
            ]
          },
          {
            "shirtNumber": "17",
            "playerName": "Rodriguez",
            "playerPosition": "Forward",
            "playerEvents": [
              {
                "event": "Substitution off",
                "eventTime": "73"
              }
            ]
          },
          {
            "shirtNumber": "22",
            "playerName": "Cedeno",
            "playerPosition": "Forward",
            "playerEvents": []
          },
          {
            "shirtNumber": "10",
            "playerName": "Mfeka",
            "playerPosition": "Forward",
            "playerEvents": [
              {
                "event": "Yellow card",
                "eventTime": "901"
              }
            ]
          },
          {
            "shirtNumber": "60",
            "playerName": "Syrel",
            "playerPosition": "Substitute",
            "playerEvents": []
          },
          {
            "shirtNumber": "46",
            "playerName": "Bracken",
            "playerPosition": "Substitute",
            "playerEvents": []
          },
          {
            "shirtNumber": "8",
            "playerName": "Donasiyano",
            "playerPosition": "Substitute",
            "playerEvents": [
              {
                "event": "Substitution on",
                "eventTime": "88"
              }
            ]
          },
          {
            "shirtNumber": "16",
            "playerName": "Her",
            "playerPosition": "Substitute",
            "playerEvents": []
          },
          {
            "shirtNumber": "19",
            "playerName": "Prentice",
            "playerPosition": "Substitute",
            "playerEvents": []
          },
          {
            "shirtNumber": "11",
            "playerName": "Reid",
            "playerPosition": "Substitute",
            "playerEvents": [
              {
                "event": "Substitution on",
                "eventTime": "84"
              }
            ]
          },
          {
            "shirtNumber": "18",
            "playerName": "Peláez",
            "playerPosition": "Substitute",
            "playerEvents": [
              {
                "event": "Substitution on",
                "eventTime": "73"
              }
            ]
          }
        ]
      }
    },
    {
      "awayTeam": "Sacramento Republic FC",
      "formation": "3-4-2-1",
      "score": "1",
      "lineup": {
        "managerName": "Briggs",
        "players": [
          {
            "shirtNumber": "1",
            "playerName": "Saldaña",
            "playerPosition": "Goalkeeper",
            "playerEvents": []
          },
          {
            "shirtNumber": "4",
            "playerName": "Desmond",
            "playerPosition": "Defender",
            "playerEvents": [
              {
                "event": "Substitution off",
                "eventTime": "64"
              }
            ]
          },
          {
            "shirtNumber": "24",
            "playerName": "Donovan",
            "playerPosition": "Defender",
            "playerEvents": [
              {
                "event": "Yellow card",
                "eventTime": "90"
              }
            ]
          },
          {
            "shirtNumber": "6",
            "playerName": "Wiedt",
            "playerPosition": "Defender",
            "playerEvents": []
          },
          {
            "shirtNumber": "2",
            "playerName": "Gurr",
            "playerPosition": "Midfielder",
            "playerEvents": []
          },
          {
            "shirtNumber": "3",
            "playerName": "Viader",
            "playerPosition": "Midfielder",
            "playerEvents": [
              {
                "event": "Yellow card",
                "eventTime": "67"
              }
            ]
          },
          {
            "shirtNumber": "20",
            "playerName": "LaGrassa",
            "playerPosition": "Midfielder",
            "playerEvents": [
              {
                "event": "Yellow card",
                "eventTime": "456"
              },
              {
                "event": "Substitution off",
                "eventTime": "45"
              }
            ]
          },
          {
            "shirtNumber": "29",
            "playerName": "López",
            "playerPosition": "Midfielder",
            "playerEvents": [
              {
                "event": "Yellow card",
                "eventTime": "67"
              },
              {
                "event": "Substitution off",
                "eventTime": "902"
              }
            ]
          },
          {
            "shirtNumber": "9",
            "playerName": "Herrera",
            "playerPosition": "Forward",
            "playerEvents": [
              {
                "event": "Penalty scored",
                "eventTime": "3"
              },
              {
                "event": "Substitution off",
                "eventTime": "45"
              }
            ]
          },
          {
            "shirtNumber": "7",
            "playerName": "Keko",
            "playerPosition": "Forward",
            "playerEvents": [
              {
                "event": "Substitution off",
                "eventTime": "70"
              }
            ]
          },
          {
            "shirtNumber": "11",
            "playerName": "Cicerone",
            "playerPosition": "Forward",
            "playerEvents": []
          },
          {
            "shirtNumber": "31",
            "playerName": "Vitiello",
            "playerPosition": "Substitute",
            "playerEvents": []
          },
          {
            "shirtNumber": "5",
            "playerName": "Timmer",
            "playerPosition": "Substitute",
            "playerEvents": [
              {
                "event": "Substitution on",
                "eventTime": "64"
              }
            ]
          },
          {
            "shirtNumber": "96",
            "playerName": "Felipe",
            "playerPosition": "Substitute",
            "playerEvents": [
              {
                "event": "Substitution on",
                "eventTime": "45"
              }
            ]
          },
          {
            "shirtNumber": "8",
            "playerName": "Rodrigo López",
            "playerPosition": "Substitute",
            "playerEvents": [
              {
                "event": "Substitution on",
                "eventTime": "70"
              }
            ]
          },
          {
            "shirtNumber": "22",
            "playerName": "Parano",
            "playerPosition": "Substitute",
            "playerEvents": []
          },
          {
            "shirtNumber": "19",
            "playerName": "Nick Ross",
            "playerPosition": "Substitute",
            "playerEvents": [
              {
                "event": "Substitution on",
                "eventTime": "902"
              }
            ]
          },
          {
            "shirtNumber": "10",
            "playerName": "Lewis",
            "playerPosition": "Substitute",
            "playerEvents": [
              {
                "event": "Substitution on",
                "eventTime": "45"
              }
            ]
          }
        ]
      }
    }
  ],
  "stats": {
    "GENERAL_STATS": {
      "home": {
        "Possession": "61.5%",
        "Duels_Success_Rate": "58.2%",
        "Ariel_Duels_Won": "39.4%",
        "Interceptions": "8",
        "Offsides": "1",
        "Corners_Won": "11"
      },
      "away": {
        "Possession": "38.5%",
        "Duels_Success_Rate": "41.8%",
        "Ariel_Duels_Won": "60.6%",
        "Interceptions": "8",
        "Offsides": "2",
        "Corners_Won": "2"
      }
    },
    "DISTRIBUTION_STATS": {
      "home": {
        "Passes": "539",
        "Long_Passes": "52",
        "Passing_Accuracy": "82.6%",
        "Passing_Accuracy_In_Opponent_Half": "73.3%",
        "Crosses": "25",
        "Crossing_Accuracy": "12.0%"
      },
      "away": {
        "Passes": "342",
        "Long_Passes": "53",
        "Passing_Accuracy": "73.1%",
        "Passing_Accuracy_In_Opponent_Half": "64.6%",
        "Crosses": "6",
        "Crossing_Accuracy": "33.3%"
      }
    },
    "ATTACK_STATS": {
      "home": {
        "Goals": "0",
        "Shots": "20",
        "Shots_On_Target": "6",
        "Blocked_Shots": "9",
        "Shots_Outside_Box": "9",
        "Shots_Inside_Box": "11",
        "Shooting_Accuracy": "30.0%"
      },
      "away": {
        "Goals": "1",
        "Shots": "7",
        "Shots_On_Target": "3",
        "Blocked_Shots": "1",
        "Shots_Outside_Box": "1",
        "Shots_Inside_Box": "6",
        "Shooting_Accuracy": "42.9%"
      }
    },
    "DEFENSE_STATS": {
      "home": {
        "Tackles": "14",
        "Tackle_Success_Rate": "71.4%",
        "Clearances": "7"
      },
      "away": {
        "Tackles": "7",
        "Tackle_Success_Rate": "57.1%",
        "Clearances": "47"
      }
    },
    "DISCIPLINE_STATS": {
      "home": {
        "Fouls_Conceded": "10",
        "Yellow_Cards": "2",
        "Red_Cards": "0"
      },
      "away": {
        "Fouls_Conceded": "17",
        "Yellow_Cards": "4",
        "Red_Cards": "0"
      }
    }
  },
  "events": [
    {
      "time": "1'",
      "event": "Foul by Matthew LaGrassa (Sacramento Republic)."
    },
    {
      "time": "1'",
      "event": "Napo Matsoso (Oakland Roots) wins a free kick in the defensive half."
    },
    {
      "time": "2'",
      "event": "Penalty Sacramento Republic. Keko Gontán draws a foul in the penalty area."
    },
    {
      "time": "2'",
      "event": "Penalty conceded by Napo Matsoso (Oakland Roots) after a foul in the penalty area."
    },
    {
      "time": "3'",
      "event": "Goal!  Oakland Roots 0, Sacramento Republic 1. Juan Herrera (Sacramento Republic) converts the penalty with a right footed shot to the bottom left corner."
    },
    {
      "time": "4'",
      "event": "Arnold López (Sacramento Republic) wins a free kick in the defensive half."
    },
    {
      "time": "4'",
      "event": "Foul by Bryan Tamacas (Oakland Roots)."
    },
    {
      "time": "5'",
      "event": "Offside, Sacramento Republic. Matthew LaGrassa tries a through ball, but Russell Cicerone is caught offside."
    },
    {
      "time": "6'",
      "event": "Delay in match  because of an injury Arnold López (Sacramento Republic)."
    },
    {
      "time": "7'",
      "event": "Delay over. They are ready to continue."
    },
    {
      "time": "10'",
      "event": "Attempt missed. Juan Herrera (Sacramento Republic) header from very close range misses to the right. Assisted by Jack Gurr."
    },
    {
      "time": "10'",
      "event": "Attempt saved. Russell Cicerone (Sacramento Republic) header from the centre of the box is saved in the centre of the goal. Assisted by Juan Herrera."
    },
    {
      "time": "11'",
      "event": "Keko Gontán (Sacramento Republic) wins a free kick in the attacking half."
    },
    {
      "time": "11'",
      "event": "Foul by Daniel Barbir (Oakland Roots)."
    },
    {
      "time": "16'",
      "event": "Guillermo Diaz (Oakland Roots) wins a free kick in the defensive half."
    },
    {
      "time": "16'",
      "event": "Foul by Shane Wiedt (Sacramento Republic)."
    },
    {
      "time": "17'",
      "event": "Neveal Hackshaw (Oakland Roots) wins a free kick in the defensive half."
    },
    {
      "time": "17'",
      "event": "Foul by Juan Herrera (Sacramento Republic)."
    },
    {
      "time": "19'",
      "event": "Offside, Oakland Roots. Daniel Barbir tries a through ball, but Bryan Tamacas is caught offside."
    },
    {
      "time": "20'",
      "event": "Foul by Damià Viader (Sacramento Republic)."
    },
    {
      "time": "20'",
      "event": "Jeciel Cedeño (Oakland Roots) wins a free kick in the defensive half."
    },
    {
      "time": "24'",
      "event": "Attempt blocked. Johnny Rodriguez (Oakland Roots) right footed shot from outside the box is blocked. Assisted by Jeciel Cedeño."
    },
    {
      "time": "24'",
      "event": "Corner,  Oakland Roots. Conceded by Conor Donovan."
    },
    {
      "time": "25'",
      "event": "Foul by Matthew LaGrassa (Sacramento Republic)."
    },
    {
      "time": "25'",
      "event": "Johnny Rodriguez (Oakland Roots) wins a free kick in the attacking half."
    },
    {
      "time": "27'",
      "event": "Attempt saved. Lindo Mfeka (Oakland Roots) left footed shot from outside the box is saved in the centre of the goal."
    },
    {
      "time": "27'",
      "event": "Attempt blocked. Napo Matsoso (Oakland Roots) right footed shot from the right side of the six yard box is blocked. Assisted by Jeciel Cedeño."
    },
    {
      "time": "27'",
      "event": "Attempt saved. Lindo Mfeka (Oakland Roots) left footed shot from the centre of the box is saved in the bottom left corner."
    },
    {
      "time": "28'",
      "event": "Corner,  Oakland Roots. Conceded by Jack Gurr."
    },
    {
      "time": "28'",
      "event": "Delay in match  because of an injury Carlos Saldaña (Sacramento Republic)."
    },
    {
      "time": "29'",
      "event": "Delay over. They are ready to continue."
    },
    {
      "time": "30'",
      "event": "Attempt blocked. Jeciel Cedeño (Oakland Roots) right footed shot from outside the box is blocked."
    },
    {
      "time": "30'",
      "event": "Jack Gurr (Sacramento Republic) wins a free kick in the defensive half."
    },
    {
      "time": "30'",
      "event": "Foul by Jeciel Cedeño (Oakland Roots)."
    },
    {
      "time": "31'",
      "event": "Delay in match   (Oakland Roots)."
    },
    {
      "time": "31'",
      "event": "Delay over. They are ready to continue."
    },
    {
      "time": "33'",
      "event": "Keko Gontán (Sacramento Republic) wins a free kick in the defensive half."
    },
    {
      "time": "33'",
      "event": "Foul by Napo Matsoso (Oakland Roots)."
    },
    {
      "time": "33'",
      "event": "Napo Matsoso (Oakland Roots) is shown the yellow card for a bad foul."
    },
    {
      "time": "37'",
      "event": "Foul by Lee Desmond (Sacramento Republic)."
    },
    {
      "time": "37'",
      "event": "Jeciel Cedeño (Oakland Roots) wins a free kick in the attacking half."
    },
    {
      "time": "38'",
      "event": "Attempt missed. Jeciel Cedeño (Oakland Roots) right footed shot from a difficult angle on the right is close, but misses to the right. Assisted by Lindo Mfeka."
    },
    {
      "time": "40'",
      "event": "Juan Herrera (Sacramento Republic) wins a free kick in the defensive half."
    },
    {
      "time": "40'",
      "event": "Foul by Bryan Tamacas (Oakland Roots)."
    },
    {
      "time": "42'",
      "event": "Corner,  Sacramento Republic. Conceded by Napo Matsoso."
    },
    {
      "time": "42'",
      "event": "Attempt missed. Juan Herrera (Sacramento Republic) header from the centre of the box misses to the left. Assisted by Keko Gontán with a cross following a corner."
    },
    {
      "time": "44'",
      "event": "Foul by Damià Viader (Sacramento Republic)."
    },
    {
      "time": "44'",
      "event": "Bryan Tamacas (Oakland Roots) wins a free kick in the defensive half."
    },
    {
      "time": "45'",
      "event": "Foul by Matthew LaGrassa (Sacramento Republic)."
    },
    {
      "time": "45'",
      "event": "Lindo Mfeka (Oakland Roots) wins a free kick in the attacking half."
    },
    {
      "time": "45'",
      "event": "Corner,  Oakland Roots. Conceded by Damià Viader."
    },
    {
      "time": "45'",
      "event": "Attempt blocked. Jeciel Cedeño (Oakland Roots) left footed shot from outside the box is blocked. Assisted by Lindo Mfeka."
    },
    {
      "time": "45+1'",
      "event": "Delay in match  because of an injury Neveal Hackshaw (Oakland Roots)."
    },
    {
      "time": "45+2'",
      "event": "Delay over. They are ready to continue."
    },
    {
      "time": "45+2'",
      "event": "Corner,  Oakland Roots. Conceded by Conor Donovan."
    },
    {
      "time": "45+3'",
      "event": "Foul by Juan Herrera (Sacramento Republic)."
    },
    {
      "time": "45+3'",
      "event": "Bryan Tamacas (Oakland Roots) wins a free kick in the defensive half."
    },
    {
      "time": "45+5'",
      "event": "Corner,  Oakland Roots. Conceded by Damià Viader."
    },
    {
      "time": "45+6'",
      "event": "Foul by Matthew LaGrassa (Sacramento Republic)."
    },
    {
      "time": "45+6'",
      "event": "Jeciel Cedeño (Oakland Roots) wins a free kick in the attacking half."
    },
    {
      "time": "45+6'",
      "event": "Matthew LaGrassa (Sacramento Republic) is shown the yellow card for a bad foul."
    },
    {
      "time": "45+8'",
      "event": "First Half ends, Oakland Roots 0, Sacramento Republic 1."
    },
    {
      "time": "45'",
      "event": "Substitution, Sacramento Republic. Zeiko Lewis replaces Juan Herrera."
    },
    {
      "time": "45'",
      "event": "Substitution, Sacramento Republic. Luis Rodrigues replaces Matthew LaGrassa."
    },
    {
      "time": "46'",
      "event": "Foul by Conor Donovan (Sacramento Republic)."
    },
    {
      "time": "46'",
      "event": "Johnny Rodriguez (Oakland Roots) wins a free kick on the right wing."
    },
    {
      "time": "50'",
      "event": "Attempt saved. Jeciel Cedeño (Oakland Roots) left footed shot from outside the box is saved in the centre of the goal. Assisted by Bryan Tamacas."
    },
    {
      "time": "51'",
      "event": "Attempt blocked. Russell Cicerone (Sacramento Republic) right footed shot from outside the box is blocked. Assisted by Jack Gurr."
    },
    {
      "time": "51'",
      "event": "Offside, Sacramento Republic. Russell Cicerone tries a through ball, but Jack Gurr is caught offside."
    },
    {
      "time": "52'",
      "event": "Foul by Arnold López (Sacramento Republic)."
    },
    {
      "time": "52'",
      "event": "Lindo Mfeka (Oakland Roots) wins a free kick on the left wing."
    },
    {
      "time": "53'",
      "event": "Keko Gontán (Sacramento Republic) wins a free kick in the defensive half."
    },
    {
      "time": "53'",
      "event": "Foul by Emrah Klimenta (Oakland Roots)."
    },
    {
      "time": "54'",
      "event": "Attempt saved. Daniel Barbir (Oakland Roots) left footed shot from outside the box is saved in the top left corner. Assisted by Johnny Rodriguez."
    },
    {
      "time": "55'",
      "event": "Attempt blocked. Lindo Mfeka (Oakland Roots) left footed shot from the centre of the box is blocked."
    },
    {
      "time": "57'",
      "event": "Hand ball by Guillermo Diaz (Oakland Roots)."
    },
    {
      "time": "57'",
      "event": "Attempt saved. Damià Viader (Sacramento Republic) left footed shot from the left side of the box is saved in the top right corner. Assisted by Luis Rodrigues."
    },
    {
      "time": "59'",
      "event": "Attempt blocked. Jeciel Cedeño (Oakland Roots) right footed shot from the centre of the box is blocked. Assisted by Lindo Mfeka with a headed pass."
    },
    {
      "time": "59'",
      "event": "Attempt saved. Daniel Barbir (Oakland Roots) left footed shot from outside the box is saved in the bottom left corner. Assisted by Napo Matsoso."
    },
    {
      "time": "60'",
      "event": "Corner,  Oakland Roots. Conceded by Carlos Saldaña."
    },
    {
      "time": "60'",
      "event": "Corner,  Oakland Roots. Conceded by Damià Viader."
    },
    {
      "time": "61'",
      "event": "Attempt saved. Johnny Rodriguez (Oakland Roots) left footed shot from the centre of the box is saved in the top right corner."
    },
    {
      "time": "61'",
      "event": "Keko Gontán (Sacramento Republic) wins a free kick in the attacking half."
    },
    {
      "time": "61'",
      "event": "Foul by Tarek Morad (Oakland Roots)."
    },
    {
      "time": "64'",
      "event": "Attempt missed. Lindo Mfeka (Oakland Roots) right footed shot from the centre of the box is just a bit too high. Assisted by Guillermo Diaz with a cross."
    },
    {
      "time": "64'",
      "event": "Substitution, Sacramento Republic. Jared Timmer replaces Lee Desmond."
    },
    {
      "time": "66'",
      "event": "Attempt missed. Emrah Klimenta (Oakland Roots) right footed shot from outside the box is close, but misses to the left. Assisted by Napo Matsoso."
    },
    {
      "time": "67'",
      "event": "Foul by Keko Gontán (Sacramento Republic)."
    },
    {
      "time": "67'",
      "event": "Lindo Mfeka (Oakland Roots) wins a free kick in the attacking half."
    },
    {
      "time": "67'",
      "event": "Arnold López (Sacramento Republic) is shown the yellow card."
    },
    {
      "time": "67'",
      "event": "Foul by Damià Viader (Sacramento Republic)."
    },
    {
      "time": "67'",
      "event": "Bryan Tamacas (Oakland Roots) wins a free kick on the right wing."
    },
    {
      "time": "67'",
      "event": "Damià Viader (Sacramento Republic) is shown the yellow card for a bad foul."
    },
    {
      "time": "70'",
      "event": "Attempt missed. Damià Viader (Sacramento Republic) left footed shot from the left side of the box is too high. Assisted by Zeiko Lewis."
    },
    {
      "time": "70'",
      "event": "Substitution, Sacramento Republic. Rodrigo López replaces Keko Gontán."
    },
    {
      "time": "73'",
      "event": "Substitution, Oakland Roots. Anuar Peláez replaces Johnny Rodriguez."
    },
    {
      "time": "75'",
      "event": "Foul by Luis Rodrigues (Sacramento Republic)."
    },
    {
      "time": "75'",
      "event": "Anuar Peláez (Oakland Roots) wins a free kick in the attacking half."
    },
    {
      "time": "76'",
      "event": "Attempt blocked. Bryan Tamacas (Oakland Roots) left footed shot from the right side of the box is blocked."
    },
    {
      "time": "76'",
      "event": "Corner,  Oakland Roots. Conceded by Damià Viader."
    },
    {
      "time": "77'",
      "event": "Attempt missed. Guillermo Diaz (Oakland Roots) right footed shot from the left side of the box is high and wide to the left. Assisted by Bryan Tamacas with a cross following a corner."
    },
    {
      "time": "77'",
      "event": "Jack Gurr (Sacramento Republic) wins a free kick on the right wing."
    },
    {
      "time": "77'",
      "event": "Foul by Guillermo Diaz (Oakland Roots)."
    },
    {
      "time": "78'",
      "event": "Corner,  Sacramento Republic. Conceded by Neveal Hackshaw."
    },
    {
      "time": "79'",
      "event": "Delay in match  because of an injury Neveal Hackshaw (Oakland Roots)."
    },
    {
      "time": "80'",
      "event": "Delay over. They are ready to continue."
    },
    {
      "time": "83'",
      "event": "Attempt missed. Daniel Barbir (Oakland Roots) left footed shot from outside the box is close, but misses to the left."
    },
    {
      "time": "84'",
      "event": "Substitution, Oakland Roots. Trayvone Reid replaces Bryan Tamacas."
    },
    {
      "time": "87'",
      "event": "Foul by Zeiko Lewis (Sacramento Republic)."
    },
    {
      "time": "87'",
      "event": "Neveal Hackshaw (Oakland Roots) wins a free kick in the defensive half."
    },
    {
      "time": "88'",
      "event": "Substitution, Oakland Roots. Irakoze Donasiyano replaces Tarek Morad."
    },
    {
      "time": "89'",
      "event": "Delay in match   (Oakland Roots)."
    },
    {
      "time": "90'",
      "event": "Conor Donovan (Sacramento Republic) is shown the yellow card."
    },
    {
      "time": "90+1'",
      "event": "Lindo Mfeka (Oakland Roots) is shown the yellow card."
    },
    {
      "time": "90+2'",
      "event": "Substitution, Sacramento Republic. Nicholas Ross replaces Arnold López."
    },
    {
      "time": "90+2'",
      "event": "Delay over. They are ready to continue."
    },
    {
      "time": "90+3'",
      "event": "Corner,  Oakland Roots. Conceded by Jack Gurr."
    },
    {
      "time": "90+4'",
      "event": "Corner,  Oakland Roots. Conceded by Luis Rodrigues."
    },
    {
      "time": "90+4'",
      "event": "Attempt blocked. Trayvone Reid (Oakland Roots) right footed shot from the left side of the box is blocked. Assisted by Napo Matsoso."
    },
    {
      "time": "90+6'",
      "event": "Foul by Russell Cicerone (Sacramento Republic)."
    },
    {
      "time": "90+6'",
      "event": "Guillermo Diaz (Oakland Roots) wins a free kick on the left wing."
    },
    {
      "time": "90+7'",
      "event": "Attempt blocked. Anuar Peláez (Oakland Roots) header from the right side of the six yard box is blocked. Assisted by Guillermo Diaz with a cross."
    },
    {
      "time": "90+7'",
      "event": "Corner,  Oakland Roots. Conceded by Shane Wiedt."
    },
    {
      "time": "90+8'",
      "event": "Second Half ends, Oakland Roots 0, Sacramento Republic 1."
    }
  ]
}